sdzkp/__init__.py
sdzkp/_version.py
sdzkp/elementaryabeliansubgroup.py
sdzkp/max2sat.py
sdzkp/prover.py
sdzkp/sgd.py
sdzkp/verifier.py
sdzkp/api/__init__.py
sdzkp/sdzkproto/__init__.py
sdzkp/sdzkproto/sdzkp_pb2.py
sdzkp/sdzkproto/sdzkp_pb2.pyi
sdzkp/sdzkproto/sdzkp_pb2_grpc.py
SDZKP-0.1.0.dist-info/LICENSE
SDZKP-0.1.0.dist-info/METADATA
SDZKP-0.1.0.dist-info/WHEEL
SDZKP-0.1.0.dist-info/top_level.txt
SDZKP-0.1.0.dist-info/RECORD
