Metadata-Version: 2.1
Name: SDZKP
Version: 0.1.0
Summary: SDZKP: A zero-knowledge proof using subgroup distance problem
Home-page: https://github.com/cansubetin/sdzkp
Author: Cansu Betin Onur
Author-email: cansubetin@gmail.com
License: GPL V3
Project-URL: Bug Tracker, https://github.com/cansubetin/sdzkp/issues
Project-URL: Simulator Website, https://github.com/cansubetin/sdzkp
Classifier: Programming Language :: Python :: 3
Classifier: Operating System :: OS Independent
Requires-Python: >=3.12
License-File: LICENSE
